{"classifier":{"classFeatures":{"greeting":{"0":2,"1":2,"2":2,"3":2,"4":2,"5":2},"bye":{"6":3,"7":2,"8":2,"9":2,"10":2,"11":2},"smalltalk":{"11":2,"12":2,"13":2,"14":2,"15":2,"16":2}},"classTotals":{"greeting":7,"bye":7,"smalltalk":7},"totalExamples":19,"smoothing":1},"docs":[{"label":"greeting","text":["hello"]},{"label":"greeting","text":["hi"]},{"label":"greeting","text":["howdi"]},{"label":"greeting","text":["hei"]},{"label":"greeting","text":["hola"]},{"label":"greeting","text":["yo"]},{"label":"bye","text":["bye"]},{"label":"bye","text":["goodby"]},{"label":"bye","text":["good","bye"]},{"label":"bye","text":["later"]},{"label":"bye","text":["farewel"]},{"label":"bye","text":["ya"]},{"label":"smalltalk","text":["ok"]},{"label":"smalltalk","text":["okai"]},{"label":"smalltalk","text":["alright"]},{"label":"smalltalk","text":["ya"]},{"label":"smalltalk","text":["yeah"]},{"label":"smalltalk","text":["haha"]}],"features":{"hello":1,"hi":1,"howdi":1,"hei":1,"hola":1,"yo":1,"bye":2,"goodby":1,"good":1,"later":1,"farewel":1,"ya":2,"ok":1,"okai":1,"alright":1,"yeah":1,"haha":1},"stemmer":{},"lastAdded":18,"events":{"_events":{},"_eventsCount":0}}